Workbook

Sheet สรุปผล
B2: รายงานผลการทดสอบระบบ Nestly (Automated UI Testing)
B3: ระบบบริหารหอพักแบบ SaaS — หน้าเจ้าของหอ ผู้เช่า และผู้ดูแลระบบ ทดสอบผ่านเบราว์เซอร์จริง (End-to-End)
B5: รอบการทดสอบ | C5: 2026-10-29 19:00 – 19:18 (4 รอบ ดูประวัติการรันด้านล่าง)
B6: เครื่องมือ | C6: Playwright 1.62 (@playwright/test) + Chromium · Node.js 22.19
B7: สภาพแวดล้อม | C7: DEV (127.0.0.1:3317 · next dev) · Chromium (Playwright 1.62) headless · 1280×720 · PostgreSQL 17.10 (nestly_test) · Windows 11
B8: ผู้รับผิดชอบการทดสอบ
B9: รายงานละเอียด / หลักฐาน | C9: ภาพหน้าจอท้ายเคสอยู่ในโฟลเดอร์ evidence-ui/ (ชื่อไฟล์ = Test Case ID) และในคอลัมน์ O ของชีต Test Cases
B10: ช่องสีเหลือง = ให้กรอกเอง · ตัวเลขด้านล่างเป็นสูตรที่นับจากชีต Test Cases (แก้คอลัมน์ Status แล้วตัวเลขเปลี่ยนตาม)
B12: ภาพรวม
B13: ตัวชี้วัด | C13: ทั้งหมด | D13: Pass | E13: Fail | F13: Block | G13: Untested | H13: อัตราผ่าน
B14: จำนวนเคส | C14: =COUNTA('Test Cases'!$A$3:$A$300) | D14: =COUNTIF('Test Cases'!$I$3:$I$300,"Pass") | E14: =COUNTIF('Test Cases'!$I$3:$I$300,"Fail") | F14: =COUNTIF('Test Cases'!$I$3:$I$300,"Block") | G14: =COUNTIF('Test Cases'!$I$3:$I$300,"Untested") | H14: =IF(C14-G14=0,0,D14/(C14-G14))
B15: อัตราผ่าน = Pass ÷ (ทั้งหมด − Untested)
B17: ประวัติการรัน
B18: รอบ | C18: วันเวลา | D18: ทั้งหมด | E18: Pass | F18: Fail | G18: Block | H18: อัตราผ่าน
B19: รอบที่ 1 — รันทั้งชุด | C19: 2026-10-29 18:59 | D19: 57 | E19: 43 | F19: 11 | G19: 0 | H19: =IF(D19=0,0,E19/D19)
B20: รอบที่ 2 — รันซ้ำเฉพาะเคสที่ไม่ผ่าน | C20: 2026-10-29 19:12 | D20: 11 | E20: 9 | F20: 2 | G20: 0 | H20: =IF(D20=0,0,E20/D20)
B21: รอบที่ 3 — รัน keyboard-flows ทั้งไฟล์ | C21: 2026-10-29 19:17 | D21: 6 | E21: 4 | F21: 1 | G21: 0 | H21: =IF(D21=0,0,E21/D21)
B22: รอบที่ 4 — รันเคสที่ยังไม่ได้รัน | C22: 2026-10-29 19:18 | D22: 1 | E22: 1 | F22: 0 | G22: 0 | H22: =IF(D22=0,0,E22/D22)
B23: ผลสุดท้าย (ใช้ผลรอบล่าสุดของแต่ละเคส) | C23: 2026-10-29 19:18 | D23: =C14 | E23: =D14 | F23: =E14 | G23: =F14 | H23: =IF(D23=0,0,E23/D23)
B24: รอบที่ 1 ไม่ผ่าน 11 เคส ส่วนใหญ่เป็น timeout ตอนเปิดหน้าครั้งแรก เพราะ next dev --webpack คอมไพล์หน้าช้า และมี 3 เคสที่ไม่ได้รัน (Untested ในรอบนั้น) · รอบที่ 2–4 รันซ้ำตอนที่ server คอมไพล์หน้าไว้แล้ว · เทียบกับ GitHub Actions CI run #107 บน commit 24a0107 เดียวกันที่ผ่านทุก job
B26: แยกตามส่วนของระบบ / โมดูล
B27: Module / Feature | C27: ทั้งหมด | D27: Pass | E27: Fail | F27: Block | G27: Untested | H27: อัตราผ่าน
B28: Accessibility | C28: =COUNTIF('Test Cases'!$B$3:$B$300,$B28) | D28: =COUNTIFS('Test Cases'!$B$3:$B$300,$B28,'Test Cases'!$I$3:$I$300,"Pass") | E28: =COUNTIFS('Test Cases'!$B$3:$B$300,$B28,'Test Cases'!$I$3:$I$300,"Fail") | F28: =COUNTIFS('Test Cases'!$B$3:$B$300,$B28,'Test Cases'!$I$3:$I$300,"Block") | G28: =COUNTIFS('Test Cases'!$B$3:$B$300,$B28,'Test Cases'!$I$3:$I$300,"Untested") | H28: =IF(C28-G28=0,0,D28/(C28-G28))
B29: Login | C29: =COUNTIF('Test Cases'!$B$3:$B$300,$B29) | D29: =COUNTIFS('Test Cases'!$B$3:$B$300,$B29,'Test Cases'!$I$3:$I$300,"Pass") | E29: =COUNTIFS('Test Cases'!$B$3:$B$300,$B29,'Test Cases'!$I$3:$I$300,"Fail") | F29: =COUNTIFS('Test Cases'!$B$3:$B$300,$B29,'Test Cases'!$I$3:$I$300,"Block") | G29: =COUNTIFS('Test Cases'!$B$3:$B$300,$B29,'Test Cases'!$I$3:$I$300,"Untested") | H29: =IF(C29-G29=0,0,D29/(C29-G29))
B30: Super Admin Dashboard | C30: =COUNTIF('Test Cases'!$B$3:$B$300,$B30) | D30: =COUNTIFS('Test Cases'!$B$3:$B$300,$B30,'Test Cases'!$I$3:$I$300,"Pass") | E30: =COUNTIFS('Test Cases'!$B$3:$B$300,$B30,'Test Cases'!$I$3:$I$300,"Fail") | F30: =COUNTIFS('Test Cases'!$B$3:$B$300,$B30,'Test Cases'!$I$3:$I$300,"Block") | G30: =COUNTIFS('Test Cases'!$B$3:$B$300,$B30,'Test Cases'!$I$3:$I$300,"Untested") | H30: =IF(C30-G30=0,0,D30/(C30-G30))
B31: Color Contrast (WCAG) | C31: =COUNTIF('Test Cases'!$B$3:$B$300,$B31) | D31: =COUNTIFS('Test Cases'!$B$3:$B$300,$B31,'Test Cases'!$I$3:$I$300,"Pass") | E31: =COUNTIFS('Test Cases'!$B$3:$B$300,$B31,'Test Cases'!$I$3:$I$300,"Fail") | F31: =COUNTIFS('Test Cases'!$B$3:$B$300,$B31,'Test Cases'!$I$3:$I$300,"Block") | G31: =COUNTIFS('Test Cases'!$B$3:$B$300,$B31,'Test Cases'!$I$3:$I$300,"Untested") | H31: =IF(C31-G31=0,0,D31/(C31-G31))
B32: Billing Lifecycle | C32: =COUNTIF('Test Cases'!$B$3:$B$300,$B32) | D32: =COUNTIFS('Test Cases'!$B$3:$B$300,$B32,'Test Cases'!$I$3:$I$300,"Pass") | E32: =COUNTIFS('Test Cases'!$B$3:$B$300,$B32,'Test Cases'!$I$3:$I$300,"Fail") | F32: =COUNTIFS('Test Cases'!$B$3:$B$300,$B32,'Test Cases'!$I$3:$I$300,"Block") | G32: =COUNTIFS('Test Cases'!$B$3:$B$300,$B32,'Test Cases'!$I$3:$I$300,"Untested") | H32: =IF(C32-G32=0,0,D32/(C32-G32))
B33: Keyboard Access | C33: =COUNTIF('Test Cases'!$B$3:$B$300,$B33) | D33: =COUNTIFS('Test Cases'!$B$3:$B$300,$B33,'Test Cases'!$I$3:$I$300,"Pass") | E33: =COUNTIFS('Test Cases'!$B$3:$B$300,$B33,'Test Cases'!$I$3:$I$300,"Fail") | F33: =COUNTIFS('Test Cases'!$B$3:$B$300,$B33,'Test Cases'!$I$3:$I$300,"Block") | G33: =COUNTIFS('Test Cases'!$B$3:$B$300,$B33,'Test Cases'!$I$3:$I$300,"Untested") | H33: =IF(C33-G33=0,0,D33/(C33-G33))
B34: Lease Renewal | C34: =COUNTIF('Test Cases'!$B$3:$B$300,$B34) | D34: =COUNTIFS('Test Cases'!$B$3:$B$300,$B34,'Test Cases'!$I$3:$I$300,"Pass") | E34: =COUNTIFS('Test Cases'!$B$3:$B$300,$B34,'Test Cases'!$I$3:$I$300,"Fail") | F34: =COUNTIFS('Test Cases'!$B$3:$B$300,$B34,'Test Cases'!$I$3:$I$300,"Block") | G34: =COUNTIFS('Test Cases'!$B$3:$B$300,$B34,'Test Cases'!$I$3:$I$300,"Untested") | H34: =IF(C34-G34=0,0,D34/(C34-G34))
B35: Mobile Touch Target | C35: =COUNTIF('Test Cases'!$B$3:$B$300,$B35) | D35: =COUNTIFS('Test Cases'!$B$3:$B$300,$B35,'Test Cases'!$I$3:$I$300,"Pass") | E35: =COUNTIFS('Test Cases'!$B$3:$B$300,$B35,'Test Cases'!$I$3:$I$300,"Fail") | F35: =COUNTIFS('Test Cases'!$B$3:$B$300,$B35,'Test Cases'!$I$3:$I$300,"Block") | G35: =COUNTIFS('Test Cases'!$B$3:$B$300,$B35,'Test Cases'!$I$3:$I$300,"Untested") | H35: =IF(C35-G35=0,0,D35/(C35-G35))
B36: Performance (Requests) | C36: =COUNTIF('Test Cases'!$B$3:$B$300,$B36) | D36: =COUNTIFS('Test Cases'!$B$3:$B$300,$B36,'Test Cases'!$I$3:$I$300,"Pass") | E36: =COUNTIFS('Test Cases'!$B$3:$B$300,$B36,'Test Cases'!$I$3:$I$300,"Fail") | F36: =COUNTIFS('Test Cases'!$B$3:$B$300,$B36,'Test Cases'!$I$3:$I$300,"Block") | G36: =COUNTIFS('Test Cases'!$B$3:$B$300,$B36,'Test Cases'!$I$3:$I$300,"Untested") | H36: =IF(C36-G36=0,0,D36/(C36-G36))
B37: Responsive | C37: =COUNTIF('Test Cases'!$B$3:$B$300,$B37) | D37: =COUNTIFS('Test Cases'!$B$3:$B$300,$B37,'Test Cases'!$I$3:$I$300,"Pass") | E37: =COUNTIFS('Test Cases'!$B$3:$B$300,$B37,'Test Cases'!$I$3:$I$300,"Fail") | F37: =COUNTIFS('Test Cases'!$B$3:$B$300,$B37,'Test Cases'!$I$3:$I$300,"Block") | G37: =COUNTIFS('Test Cases'!$B$3:$B$300,$B37,'Test Cases'!$I$3:$I$300,"Untested") | H37: =IF(C37-G37=0,0,D37/(C37-G37))
B38: Subscription Access | C38: =COUNTIF('Test Cases'!$B$3:$B$300,$B38) | D38: =COUNTIFS('Test Cases'!$B$3:$B$300,$B38,'Test Cases'!$I$3:$I$300,"Pass") | E38: =COUNTIFS('Test Cases'!$B$3:$B$300,$B38,'Test Cases'!$I$3:$I$300,"Fail") | F38: =COUNTIFS('Test Cases'!$B$3:$B$300,$B38,'Test Cases'!$I$3:$I$300,"Block") | G38: =COUNTIFS('Test Cases'!$B$3:$B$300,$B38,'Test Cases'!$I$3:$I$300,"Untested") | H38: =IF(C38-G38=0,0,D38/(C38-G38))
B39: Session Management | C39: =COUNTIF('Test Cases'!$B$3:$B$300,$B39) | D39: =COUNTIFS('Test Cases'!$B$3:$B$300,$B39,'Test Cases'!$I$3:$I$300,"Pass") | E39: =COUNTIFS('Test Cases'!$B$3:$B$300,$B39,'Test Cases'!$I$3:$I$300,"Fail") | F39: =COUNTIFS('Test Cases'!$B$3:$B$300,$B39,'Test Cases'!$I$3:$I$300,"Block") | G39: =COUNTIFS('Test Cases'!$B$3:$B$300,$B39,'Test Cases'!$I$3:$I$300,"Untested") | H39: =IF(C39-G39=0,0,D39/(C39-G39))
... B42: Tenant Journey | C42: =COUNTIF('Test Cases'!$B$3:$B$300,$B42) | D42: =COUNTIFS('Test Cases'!$B$3:$B$300,$B42,'Test Cases'!$I$3:$I$300,"Pass") | E42: =COUNTIFS('Test Cases'!$B$3:$B$300,$B42,'Test Cases'!$I$3:$I$300,"Fail") | F42: =COUNTIFS('Test Cases'!$B$3:$B$300,$B42,'Test Cases'!$I$3:$I$300,"Block") | G42: =COUNTIFS('Test Cases'!$B$3:$B$300,$B42,'Test Cases'!$I$3:$I$300,"Untested") | H42: =IF(C42-G42=0,0,D42/(C42-G42))

Sheet แผนการทดสอบ
B2: แผนการทดสอบ (Test Plan)
B3: Nestly — การทดสอบหน้าจอแบบอัตโนมัติ (End-to-End) ก่อนขึ้นระบบจริง
B5: 1. วัตถุประสงค์
B6: • ยืนยันว่าเส้นทางหลักของผู้ใช้ทั้ง 3 บทบาท (เจ้าของหอ ผู้เช่า ผู้ดูแลระบบ) ทำงานถูกต้องบนเบราว์เซอร์จริง
B7: • ตรวจข้อกำหนดด้านการใช้งาน: คีย์บอร์ด, ความต่างสี WCAG AA, ขนาดปุ่มบนมือถือ, การแสดงผลหลายขนาดจอ และจำนวนคำขอที่หน้าเว็บยิง
B8: • ทดสอบแบบอัตโนมัติด้วย Playwright เพื่อรันซ้ำได้ทุกครั้งที่แก้โค้ด และ GitHub Actions รันให้ทุก pull request
B9: • เก็บภาพหน้าจอท้ายเคสทุกเคสเป็นหลักฐาน
B11: 2. ขอบเขตการทดสอบ
B12: อยู่ในขอบเขต (รอบนี้) | C12: 57 เคส: Accessibility 10 · Login 1 · Super Admin Dashboard 1 · Color Contrast (WCAG) 8 · Billing Lifecycle 1 · Keyboard Access 6 · Lease Renewal 1 · Mobile Touch Target 5 · Performance (Requests) 5 · Responsive 4 · Subscription Access 6 · Session Management 1 · Table Contract 3 · Owner Journey 3 · Tenant Journey 2
B13: นอกขอบเขต | C13: Firefox / Safari (WebKit) / Edge · อุปกรณ์มือถือจริง (ใช้การจำลองขนาดจอแทน) · การทดสอบโหลด · การส่งอีเมลจริง · ระบบชำระเงินจริง
B14: ทดสอบในระดับอื่นแล้ว | C14: ตรรกะคิดเงิน สิทธิ์ การตรวจข้อมูล และ API ครอบด้วย Vitest (ดูไฟล์ Nestly-API-Test-Report.xlsx)
B16: 3. รายการที่ทดสอบ (Test Items)
B17: ส่วนของระบบ | C17: ที่อยู่ (ระบบทดสอบ) | D17: เทคโนโลยี | E17: บัญชีทดสอบ
B18: เว็บแอป (หน้าจอ + API) | C18: http://127.0.0.1:3317 | D18: Next.js 16 + React 19 + Tailwind CSS 4 | E18: e2e-owner@example.test (เจ้าของหอ 2 หอ) · e2e-tenant@example.test (ผู้เช่าหลักห้อง E101) · e2e-super-admin@example.test (ผู้ดูแลระบบ) — รหัสผ่านอยู่ใน tests/e2e/fixtures.ts
B19: ฐานข้อมูล | C19: 127.0.0.1:55432 / nestly_test | D19: PostgreSQL 17 (Docker, tmpfs) + Prisma 7.9 | E19: สร้างใหม่ทุกรอบโดย tests/e2e/global-setup.ts
B21: 4. สภาพแวดล้อมการทดสอบ
B22: เครื่อง/เบราว์เซอร์ | C22: Windows 11 · Chromium ของ Playwright 1.62 แบบ headless · ขนาดจอ 1280×720 (บางเคสตั้ง 320–1440 px)
B23: แยกจาก dev | C23: ฐานข้อมูลทดสอบชื่อต้องมีคำว่า test (สคริปต์ปฏิเสธถ้าชี้ผิดฐาน) · ใช้พอร์ต 3317 แยกจาก dev server ที่พอร์ต 3000
B24: ไฟล์อัปโหลด | C24: STORAGE_TYPE=local · เก็บที่ ./storage/e2e-documents
B25: หมายเหตุรอบนี้ | C25: รันจากสำเนาโค้ดของ commit 24a0107 ด้วย next dev --webpack และ Chromium ตัวเต็ม เพราะมี dev server อีกตัวเปิดอยู่ในโฟลเดอร์โปรเจกต์ (Next.js ไม่ให้เปิดสองตัวในโฟลเดอร์เดียว) · CI ใช้ Turbopack และ headless shell ตามค่าปกติ
B27: 5. เกณฑ์เริ่มและเกณฑ์จบ
B28: เกณฑ์เริ่ม (Entry) | C28: ฐานทดสอบ migrate ครบ · global-setup สร้างบัญชีและข้อมูลตั้งต้นสำเร็จ · /api/health ตอบ 200
B29: เกณฑ์จบ (Exit) | C29: ทุกเคสรันครบ ไม่มีเคส Untested · อัตราผ่าน 100% หรือเคสที่ไม่ผ่านมี Defect ID และแผนแก้
B30: การรันซ้ำ | C30: npm run test:e2e (หรือ npm run test:e2e:subscription ให้สคริปต์ยกฐานทดสอบเอง)

Sheet กลยุทธ์การทดสอบ
B2: กลยุทธ์การทดสอบ (Test Strategy)
B3: ทดสอบอะไร ด้วยวิธีไหน ระดับไหน และจัดการผลอย่างไร
B5: 1. ระดับการทดสอบ (Test Levels)
B6: ระดับ | C6: เครื่องมือ | D6: ทดสอบอะไร | E6: รันเมื่อไร
B7: Static Analysis | C7: TypeScript strict · ESLint · SonarQube | D7: ชนิดข้อมูล กลิ่นโค้ด ช่องโหว่ ความซับซ้อน | E7: ทุก push / pull request (CI job quality)
B8: Unit | C8: Vitest | D8: ตรรกะธุรกิจ การตรวจข้อมูล (Zod) การคำนวณเงิน | E8: ทุก push / pull request
B9: Integration | C9: Vitest + PostgreSQL | D9: route handler, service, สิทธิ์ และ transaction กับฐานข้อมูลจริง | E9: ทุก push / pull request (CI job integration)
B10: End-to-End (UI) | C10: Playwright + Chromium | D10: สิ่งที่ผู้ใช้เห็นและกดจริง ทั้ง 3 บทบาท | E10: ทุก push / pull request (CI job e2e) · retry 2 ครั้งใน CI
B11: Smoke (container) | C11: Docker Compose + curl | D11: image รันได้ด้วย user ที่ไม่ใช่ root, migrate ผ่าน, /api/health ตอบ | E11: ทุก push / pull request (CI job docker)
B13: 2. ประเภทและเทคนิคการทดสอบ
B14: เทคนิค | C14: ตัวอย่างในรายงานนี้
B15: Positive (ทางที่ถูก) | C15: TC_UI_BILL_001, TC_UI_LEASE_001, TC_UI_TENANT_002
B16: Negative (ข้อมูลผิด) | C16: TC_UI_LOGIN_001
B17: Security | C17: TC_UI_LOGIN_001, TC_UI_SESSION_001
B18: State / Workflow | C18: TC_UI_SUB_001, TC_UI_SUB_002, TC_UI_SUB_003, TC_UI_SUB_004, TC_UI_A11Y_007
B19: Responsive / Mobile | C19: TC_UI_MOB_001, TC_UI_MOB_002, TC_UI_MOB_003, TC_UI_MOB_004, TC_UI_RESP_001
B20: Accessibility (WCAG AA) | C20: TC_UI_A11Y_002, TC_UI_A11Y_003, TC_UI_A11Y_004, TC_UI_A11Y_005, TC_UI_A11Y_006
B21: Performance (จำนวนคำขอ) | C21: TC_UI_PERF_001, TC_UI_PERF_002, TC_UI_PERF_003, TC_UI_PERF_004, TC_UI_PERF_005
B23: 3. การจัดการข้อมูลทดสอบ
B24: ข้อมูลตั้งต้น | C24: tests/e2e/global-setup.ts ลบข้อมูลของหอทดสอบแล้วใส่ใหม่ทุกรอบด้วย SQL แบบ parameterized: หอ 2 หอ ห้อง E101/F201 ผู้เช่า สัญญา CTR-E2E-E101 บิล E2E-202607-E101
B25: ข้อมูลที่เทสต์สร้าง | C25: เคสรอบบิลครบวงจรสร้างเจ้าของหอ หอพัก และผู้เช่าใหม่ ชื่อลงท้ายด้วยเวลาและตัวสุ่ม จึงรันซ้ำได้โดยไม่ชนกัน
B26: ความปลอดภัยของข้อมูล | C26: ใช้โดเมน .test ที่ไม่มีอยู่จริง · ไม่มีรหัสผ่านจริงในรายงาน · สคริปต์ปฏิเสธฐานที่ชื่อไม่มีคำว่า test
B28: 4. การจัดการผลและข้อบกพร่อง
B29: • Status ใช้ 4 ค่า: Pass / Fail / Block (รันไม่ได้เพราะสภาพแวดล้อม) / Untested
B30: • เคส Fail ต้องวิเคราะห์ก่อนว่าเป็นบัคของระบบหรือของสคริปต์ ถ้าเป็นบัคของระบบจึงออก Defect ID ในชีต Defects
B31: • แก้แล้วต้องรันเคสเดิมซ้ำและบันทึกผล Retest พร้อมหลักฐาน

Sheet Test Cases
A1: 1. ข้อมูลระดับโครงสร้างและเคสทดสอบ (Test Setup) | H1: 2. ผลการทดสอบและการแจ้งบัค (Execution & Bug Tracking) | L1: 3. การบันทึกและจัดการ (Metadata & Evidence)
A2: Test Case ID | B2: Module / Feature | C2: Test Scenario / Title | D2: Pre-conditions | E2: Test Steps | F2: Test Data | G2: Expected Result | H2: Actual Result | I2: Status | J2: Defect ID / Bug Link | K2: Severity / Priority | L2: Environment | M2: Tester Name | N2: Execution Date | O2: Screenshot / Evidence Link | P2: Remarks / Note
A3: TC_UI_A11Y_001 | B3: Accessibility | C3: ผลค้นหาว่างแสดงกะทัดรัด อยู่กลาง และสีแดงอ่านชัด | D3: global-setup ล้างและใส่ข้อมูลทดสอบชุดใหม่ (หอ E2E 2 หอ · ห้อง E101 · ผู้เช่า E2E Tenant · คำขอเข้าพักที่รออนุมัติ) · เข้าสู่ระบบด้วย e2e-owner@example.test | E3: 1. เปิดหน้าสัญญาเช่า 2. ค้นหาคำที่ไม่มีผล 3. วัดตำแหน่งและ contrast ของข้อความ | F3: คำค้นที่ไม่มีผล | G3: ข้อความอยู่กลาง ขนาดกะทัดรัด · contrast ≥ 4.5:1 | H3: ผลตรงตามที่คาดหวัง — assertion ผ่านครบ (11.72 วินาที) | I3: Pass | L3: DEV (127.0.0.1:3317 · next dev) · Chromium (Playwright 1.62) headless · 1280×720 · PostgreSQL 17.10 (nestly_test) · Windows 11 | M3: Playwright 1.62 (อัตโนมัติ) | N3: 46324.8 | O3: evidence-ui/TC_UI_A11Y_001.png | P3: ผลจากรอบที่ 2 — รันซ้ำเฉพาะเคสที่ไม่ผ่าน สคริปต์: tests/e2e/accessibility-controls.spec.ts ชื่อเทสต์: Owner accessibility controls › empty search results are compact, centered and clearly red
A4: TC_UI_A11Y_002 | B4: Accessibility | C4: แถบเครื่องมือแก้เอกสารบอกสถานะปุ่ม ใช้ลูกศรได้ และมี tooltip เมื่อ focus | D4: global-setup ล้างและใส่ข้อมูลทดสอบชุดใหม่ (หอ E2E 2 หอ · ห้อง E101 · ผู้เช่า E2E Tenant · คำขอเข้าพักที่รออนุมัติ) · เข้าสู่ระบบด้วย e2e-owner@example.test | E4: 1. เปิดหน้าแก้เทมเพลตสัญญา 2. ใช้ ArrowRight/Home/End ในแถบเครื่องมือ 3. ตรวจ aria-pressed และ tooltip | F4: /settings/documents/contract/edit | G4: focus ย้ายตามลูกศร · ปุ่มเปิด/ปิดมี aria-pressed · tooltip แสดงเมื่อ focus | H4: ผลตรงตามที่คาดหวัง — assertion ผ่านครบ (9.49 วินาที) | I4: Pass | L4: DEV (127.0.0.1:3317 · next dev) · Chromium (Playwright 1.62) headless · 1280×720 · PostgreSQL 17.10 (nestly_test) · Windows 11 | M4: Playwright 1.62 (อัตโนมัติ) | N4: 46324.792 | O4: evidence-ui/TC_UI_A11Y_002.png | P4: ผลจากรอบที่ 1 — รันทั้งชุด สคริปต์: tests/e2e/accessibility-controls.spec.ts ชื่อเทสต์: Owner accessibility controls › document toolbar exposes toggle state, keyboard navigation and focus tooltips
A5: TC_UI_A11Y_003 | B5: Accessibility | C5: กรอบ focus ของลิงก์ ช่องกรอก การ์ด และแท็บเป็นแบบเดียวกัน | D5: global-setup ล้างและใส่ข้อมูลทดสอบชุดใหม่ (หอ E2E 2 หอ · ห้อง E101 · ผู้เช่า E2E Tenant · คำขอเข้าพักที่รออนุมัติ) · เข้าสู่ระบบด้วย e2e-owner@example.test | E5: 1. เปิดหน้าประกาศและห้องพัก 2. Tab ไปยังองค์ประกอบแต่ละแบบ 3. อ่าน outline ที่คำนวณได้ | F5: ลิงก์ · ช่องกรอก · การ์ด · แท็บ | G5: ทุกแบบมีกรอบ focus ที่มองเห็นและสไตล์เดียวกัน | H5: ผลตรงตามที่คาดหวัง — assertion ผ่านครบ (9.89 วินาที) | I5: Pass | L5: DEV (127.0.0.1:3317 · next dev) · Chromium (Playwright 1.62) headless · 1280×720 · PostgreSQL 17.10 (nestly_test) · Windows 11 | M5: Playwright 1.62 (อัตโนมัติ) | N5: 46324.792 | O5: evidence-ui/TC_UI_A11Y_003.png | P5: ผลจากรอบที่ 1 — รันทั้งชุด สคริปต์: tests/e2e/accessibility-controls.spec.ts ชื่อเทสต์: Owner accessibility controls › focus indicators are consistent for links, fields, cards and tabs
A6: TC_UI_A11Y_004 | B6: Accessibility | C6: dropdown ใช้คีย์บอร์ดได้ครบและพิมพ์ตัวอักษรเพื่อกระโดดได้ (type-ahead) | D6: global-setup ล้างและใส่ข้อมูลทดสอบชุดใหม่ (หอ E2E 2 หอ · ห้อง E101 · ผู้เช่า E2E Tenant · คำขอเข้าพักที่รออนุมัติ) · เข้าสู่ระบบด้วย e2e-owner@example.test | E6: 1. เปิดหน้าบิล 2. ใช้ ArrowDown/End/Home 3. พิมพ์ตัวอักษร 4. Enter / Space / Escape | F6: dropdown ตัวกรองสถานะ | G6: ตัวเลือกที่ active ย้ายถูกต้อง · type-ahead ไปตัวเลือกที่ตรง · Esc ปิด | H6: ผลตรงตามที่คาดหวัง — assertion ผ่านครบ (4.28 วินาที) | I6: Pass | L6: DEV (127.0.0.1:3317 · next dev) · Chromium (Playwright 1.62) headless · 1280×720 · PostgreSQL 17.10 (nestly_test) · Windows 11 | M6: Playwright 1.62 (อัตโนมัติ) | N6: 46324.792 | O6: evidence-ui/TC_UI_A11Y_004.png | P6: ผลจากรอบที่ 1 — รันทั้งชุด สคริปต์: tests/e2e/accessibility-controls.spec.ts ชื่อเทสต์: Owner accessibility controls › dropdown supports complete keyboard navigation and type-ahead
A7: TC_UI_A11Y_005 | B7: Accessibility | C7: เมนูคีย์บอร์ด tooltip contrast และปุ่มมือถือเป็นไปตามข้อกำหนด UI (เจ้าของหอ) | D7: global-setup ล้างและใส่ข้อมูลทดสอบชุดใหม่ (หอ E2E 2 หอ · ห้อง E101 · ผู้เช่า E2E Tenant · คำขอเข้าพักที่รออนุมัติ) · เข้าสู่ระบบด้วย e2e-owner@example.test | E7: 1. เปิดเมนูจัดการด้วยคีย์บอร์ด 2. ตรวจ tooltip และ contrast 3. ตั้งจอมือถือแล้ววัดขนาดปุ่ม | F7: viewport มือถือ | G7: เมนูทำงาน · contrast ผ่าน · ปุ่ม ≥ 44×44 px | H7: ผลตรงตามที่คาดหวัง — assertion ผ่านครบ (5.93 วินาที) | I7: Pass | L7: DEV (127.0.0.1:3317 · next dev) · Chromium (Playwright 1.62) headless · 1280×720 · PostgreSQL 17.10 (nestly_test) · Windows 11 | M7: Playwright 1.62 (อัตโนมัติ) | N7: 46324.792 | O7: evidence-ui/TC_UI_A11Y_005.png | P7: ผลจากรอบที่ 1 — รันทั้งชุด สคริปต์: tests/e2e/accessibility-controls.spec.ts ชื่อเทสต์: Owner accessibility controls › keyboard menu, tooltip, contrast and mobile targets meet the UI contract
A8: TC_UI_A11Y_006 | B8: Accessibility | C8: tooltip คีย์บอร์ด contrast และปุ่มมือถือเป็นไปตามข้อกำหนด UI (ผู้เช่า/Super Admin) | D8: global-setup ล้างและใส่ข้อมูลทดสอบชุดใหม่ (หอ E2E 2 หอ · ห้อง E101 · ผู้เช่า E2E Tenant · คำขอเข้าพักที่รออนุมัติ) · เข้าสู่ระบบทั้ง 3 บทบาท | E8: 1. Tab ไปปุ่มไอคอน 2. ตรวจ tooltip และ contrast 3. ตั้งจอมือถือแล้ววัดขนาดปุ่ม | F8: viewport มือถือ | G8: tooltip แสดงเมื่อ focus · contrast ผ่าน · ปุ่ม ≥ 44×44 px | H8: ผลตรงตามที่คาดหวัง — assertion ผ่านครบ (6.13 วินาที) | I8: Pass | L8: DEV (127.0.0.1:3317 · next dev) · Chromium (Playwright 1.62) headless · 1280×720 · PostgreSQL 17.10 (nestly_test) · Windows 11 | M8: Playwright 1.62 (อัตโนมัติ) | N8: 46324.792 | O8: evidence-ui/TC_UI_A11Y_006.png | P8: ผลจากรอบที่ 1 — รันทั้งชุด สคริปต์: tests/e2e/accessibility-controls.spec.ts ชื่อเทสต์: Tenant accessibility controls › keyboard tooltip, contrast and mobile targets meet the UI contract
A9: TC_UI_LOGIN_001 | B9: Login | C9: เข้าสู่ระบบด้วยบัญชีที่ไม่มีอยู่ ระบบไม่บอกว่าบัญชีมีจริงหรือไม่ | D9: อยู่หน้า /login ยังไม่เข้าสู่ระบบ | E9: 1. เปิด /login 2. กรอกอีเมลที่ไม่มีในระบบ 3. กรอกรหัสผ่านผิด 4. กดเข้าสู่ระบบ | F9: Email: unknown@example.com Password: incorrect-password | G9: แสดง alert "อีเมลหรือรหัสผ่านไม่ถูกต้อง" และยังอยู่หน้า /login | H9: ผลตรงตามที่คาดหวัง — assertion ผ่านครบ (3.44 วินาที) | I9: Pass | L9: DEV (127.0.0.1:3317 · next dev) · Chromium (Playwright 1.62) headless · 1280×720 · PostgreSQL 17.10 (nestly_test) · Windows 11 | M9: Playwright 1.62 (อัตโนมัติ) | N9: 46324.792 | O9: evidence-ui/TC_UI_LOGIN_001.png | P9: ผลจากรอบที่ 1 — รันทั้งชุด สคริปต์: tests/e2e/auth-dashboard.spec.ts ชื่อเทสต์: rejects invalid credentials without leaking account state
A10: TC_UI_SADMIN_001 | B10: Super Admin Dashboard | C10: Super Admin เข้าสู่ระบบแล้วเปิดแดชบอร์ด SaaS และเมนูหลักได้ครบ | D10: global-setup ล้างและใส่ข้อมูลทดสอบชุดใหม่ (หอ E2E 2 หอ · ห้อง E101 · ผู้เช่า E2E Tenant · คำขอเข้าพักที่รออนุมัติ) | E10: 1. เปิด /login แล้วเข้าสู่ระบบด้วย Super Admin 2. ตรวจหน้าแดชบอร์ด 3. กดเมนูหลักทีละเมนู | F10: Email: e2e-super-admin@example.test Password: (ค่าทดสอบจาก tests/e2e/fixtures.ts) | G10: ไปที่ /super-admin มีหัวข้อ "แดชบอร์ด" และ "MRR" · ทุกเมนูเปิดหน้าที่ถูกต้องพร้อมหัวข้อของหน้า | H10: ผลตรงตามที่คาดหวัง — assertion ผ่านครบ (12.39 วินาที) | I10: Pass | L10: DEV (127.0.0.1:3317 · next dev) · Chromium (Playwright 1.62) headless · 1280×720 · PostgreSQL 17.10 (nestly_test) · Windows 11 | M10: Playwright 1.62 (อัตโนมัติ) | N10: 46324.792 | O10: evidence-ui/TC_UI_SADMIN_001.png | P10: ผลจากรอบที่ 1 — รันทั้งชุด สคริปต์: tests/e2e/auth-dashboard.spec.ts ชื่อเทสต์: super admin can open the aggregated SaaS dashboard
A11: TC_UI_CONTRAST_001 | B11: Color Contrast (WCAG) | C11: ข้อความและปุ่มทุกสถานะมีความต่างสีผ่าน WCAG AA | D11: global-setup ล้างและใส่ข้อมูลทดสอบชุดใหม่ (หอ E2E 2 หอ · ห้อง E101 · ผู้เช่า E2E Tenant · คำขอเข้าพักที่รออนุมัติ) · เข้าสู่ระบบด้วย e2e-owner@example.test | E11: 1. เปิดหน้าประกาศและมิเตอร์น้ำ 2. คำนวณ contrast ของหัวข้อ ลิงก์ ปุ่ม ทั้ง default/hover/focus | F11: เกณฑ์ข้อความ 4.5:1 | G11: ทุกจุดมี contrast ≥ 4.5:1 | H11: ผลตรงตามที่คาดหวัง — assertion ผ่านครบ (4.97 วินาที) | I11: Pass | L11: DEV (127.0.0.1:3317 · next dev) · Chromium (Playwright 1.62) headless · 1280×720 · PostgreSQL 17.10 (nestly_test) · Windows 11 | M11: Playwright 1.62 (อัตโนมัติ) | N11: 46324.801 | O11: evidence-ui/TC_UI_CONTRAST_001.png | P11: ผลจากรอบที่ 2 — รันซ้ำเฉพาะเคสที่ไม่ผ่าน สคริปต์: tests/e2e/contrast.spec.ts ชื่อเทสต์: computed WCAG contrast › text and interactive states meet WCAG AA
A12: TC_UI_CONTRAST_002 | B12: Color Contrast (WCAG) | C12: ไอคอนมีความต่างสีพอทั้ง default/hover/focus | D12: global-setup ล้างและใส่ข้อมูลทดสอบชุดใหม่ (หอ E2E 2 หอ · ห้อง E101 · ผู้เช่า E2E Tenant · คำขอเข้าพักที่รออนุมัติ) · เข้าสู่ระบบด้วย e2e-owner@example.test | E12: 1. เปิดหน้าประกาศ 2. วัด contrast ของไอคอน | F12: เกณฑ์ non-text 3:1 | G12: ไอคอนทุกสถานะ ≥ 3:1 | H12: ผลตรงตามที่คาดหวัง — assertion ผ่านครบ (4.65 วินาที) | I12: Pass | L12: DEV (127.0.0.1:3317 · next dev) · Chromium (Playwright 1.62) headless · 1280×720 · PostgreSQL 17.10 (nestly_test) · Windows 11 | M12: Playwright 1.62 (อัตโนมัติ) | N12: 46324.792 | O12: evidence-ui/TC_UI_CONTRAST_002.png | P12: ผลจากรอบที่ 1 — รันทั้งชุด สคริปต์: tests/e2e/contrast.spec.ts ชื่อเทสต์: computed WCAG contrast › icons expose non-text contrast in default, hover and focus states
A13: TC_UI_CONTRAST_003 | B13: Color Contrast (WCAG) | C13: ป้ายสถานะ (badge) อ่านได้ชัด | D13: global-setup ล้างและใส่ข้อมูลทดสอบชุดใหม่ (หอ E2E 2 หอ · ห้อง E101 · ผู้เช่า E2E Tenant · คำขอเข้าพักที่รออนุมัติ) · เข้าสู่ระบบด้วย e2e-owner@example.test | E13: 1. วัด contrast ของ badge สถานะเผยแพร่ | F13: เกณฑ์ 4.5:1 | G13: badge ≥ 4.5:1 | H13: ผลตรงตามที่คาดหวัง — assertion ผ่านครบ (4.27 วินาที) | I13: Pass | L13: DEV (127.0.0.1:3317 · next dev) · Chromium (Playwright 1.62) headless · 1280×720 · PostgreSQL 17.10 (nestly_test) · Windows 11 | M13: Playwright 1.62 (อัตโนมัติ) | N13: 46324.793 | O13: evidence-ui/TC_UI_CONTRAST_003.png | P13: ผลจากรอบที่ 1 — รันทั้งชุด สคริปต์: tests/e2e/contrast.spec.ts ชื่อเทสต์: computed WCAG contrast › badges meet text contrast requirements
A14: TC_UI_CONTRAST_004 | B14: Color Contrast (WCAG) | C14: ขอบช่องกรอกและปุ่มมองเห็นชัด | D14: global-setup ล้างและใส่ข้อมูลทดสอบชุดใหม่ (หอ E2E 2 หอ · ห้อง E101 · ผู้เช่า E2E Tenant · คำขอเข้าพักที่รออนุมัติ) · เข้าสู่ระบบด้วย e2e-owner@example.test | E14: 1. วัด contrast ของเส้นขอบช่องกรอกและปุ่มกับพื้นหลัง | F14: เกณฑ์ non-text 3:1 | G14: เส้นขอบ ≥ 3:1 | H14: ผลตรงตามที่คาดหวัง — assertion ผ่านครบ (4.07 วินาที) | I14: Pass | L14: DEV (127.0.0.1:3317 · next dev) · Chromium (Playwright 1.62) headless · 1280×720 · PostgreSQL 17.10 (nestly_test) · Windows 11 | M14: Playwright 1.62 (อัตโนมัติ) | N14: 46324.793 | O14: evidence-ui/TC_UI_CONTRAST_004.png | P14: ผลจากรอบที่ 1 — รันทั้งชุด สคริปต์: tests/e2e/contrast.spec.ts ชื่อเทสต์: computed WCAG contrast › input and button boundaries meet non-text contrast requirements
... A59: TC_UI_TENANT_002 | B59: Tenant Journey | C59: ผู้เช่าแจ้งซ่อมและส่งข้อความแชทถึงหอพัก | D59: global-setup ล้างและใส่ข้อมูลทดสอบชุดใหม่ (หอ E2E 2 หอ · ห้อง E101 · ผู้เช่า E2E Tenant · คำขอเข้าพักที่รออนุมัติ) · เข้าสู่ระบบด้วย e2e-tenant@example.test | E59: 1. เมนูแจ้งเรื่อง → กดแจ้งเรื่อง 2. กรอกหัวข้อ รายละเอียด เลือกความเร่งด่วน "ด่วน" → ส่งเรื่อง 3. กดเปิดแชทกับหอพัก → พิมพ์ข้อความ → ส่งข้อความ | F59: หัวข้อ: "ก๊อกน้ำ E2E รั่ว" · ความเร่งด่วน: ด่วน · ข้อความแชทสุ่มทุกรอบ | G59: เรื่อง "ก๊อกน้ำ E2E รั่ว" ปรากฏพร้อมป้าย "ด่วน" · ข้อความแชทแสดงในหน้าต่างแชท | H59: ไม่ผ่าน: Error: expect(locator).toBeVisible() failed Locator: getByRole('dialog', { name: 'แชทกับหอพัก' }).getByText('ข้อความ E2E 1793276140216', { exact: true }) Expected: visible Timeout: 5000ms Error: element(s) not found Call log: - Expect "toBeVisible" with timeout 5000ms - waiting for getByRole('dialog', { name: 'แชทกับหอพัก' }).getByText('ข้อความ E2E 1793276140216', { exact: true }) | | I59: Fail | L59: DEV (127.0.0.1:3317 · next dev) · Chromium (Playwright 1.62) headless · 1280×720 · PostgreSQL 17.10 (nestly_test) · Windows 11 | M59: Playwright 1.62 (อัตโนมัติ) | N59: 46324.803 | O59: evidence-ui/TC_UI_TENANT_002.png | P59: ข้อสังเกต: ไม่ผ่านซ้ำในสภาพแวดล้อมรอบนี้ (next dev --webpack จากสำเนาโค้ด) อาการคือกดปุ่มแล้วหน้าไม่ตอบสนอง ตรงกับการกดก่อนหน้าโหลด JavaScript เสร็จ (hydration) · GitHub Actions CI run #107 บน commit 24a0107 เดียวกันผ่าน · ต้องรันซ้ำด้วย npm run test:e2e ตามปกติก่อนสรุปว่าเป็นบัค ผลจากรอบที่ 2 — รันซ้ำเฉพาะเคสที่ไม่ผ่าน สคริปต์: tests/e2e/tenant-owner-journeys.spec.ts ชื่อเทสต์: tenant journey › creates a repair ticket and sends a chat message

Sheet Defects
A1: รายการข้อบกพร่อง (Defect Log) — ออก Defect ID เฉพาะเคสที่วิเคราะห์แล้วว่าเป็นบัคของระบบ
A2: Defect ID | B2: Test Case ID | C2: Title | D2: Severity | E2: Priority | F2: Steps to Reproduce | G2: Expected Result | H2: Actual Result | I2: ผลกระทบต่อผู้ใช้ | J2: แนวทางแก้ (Suggested Fix) | K2: ไฟล์ที่เกี่ยวข้อง | L2: Evidence (ตอนพบบัค) | M2: Found Date | N2: Defect Status | O2: การแก้ไขที่ทำ | P2: ผลทดสอบซ้ำ (Retest) | Q2: หลักฐานหลังแก้
B3: TC_UI_BILL_001 | C3: รอบบิลครบวงจรผ่านหน้าจอจริง ตั้งแต่สมัครเจ้าของหอจนรับชำระเงิน | F3: 1. สร้างเจ้าของหอใหม่ (PENDING) → Super Admin อนุมัติ 2. เจ้าของหอตั้งรหัสใหม่ → ยอมรับนโยบาย → สลับหอ 3. สร้างคำเชิญ → ผู้เช่าสมัครที่ /register 4. เจ้าของหออนุมัติคำขอเข้าพัก → สร้างสัญญา (มัดจำ 7,000) 5. จดมิเตอร์น้ำและไฟ → สร้างร่างบิล → ออกบิล 6. ผู้เช่าเปิดบิล เห็น QR PromptPay → ส่งสลิป PNG 7. เจ้าของหอตรวจและยืนยันรับชำระ | G3: สมัครผู้เช่าได้ 201 "สมัครสำเร็จ" · สัญญาเป็นฉบับร่าง · มิเตอร์ "บันทึกแล้ว" · บิลยอด > 3,500 สถานะ "รอชำระ" · สลิป "รอตรวจสอบ" ยอดตรงบิล · ยืนยันแล้วบิลเป็นชำระแล้ว | H3: ไม่ผ่าน: TimeoutError: locator.click: Timeout 10000ms exceeded. Call log: - waiting for getByRole('menuitem', { name: /JD-1793275969451-d6yxjh/ }) | ^ at D:\ปี4_1\it-project\.claude\e2e-run\tests\e2e\full-billing-lifecycle.spec.ts:180:74 | I3: ข้อสังเกต: ไม่ผ่านซ้ำในสภาพแวดล้อมรอบนี้ (next dev --webpack จากสำเนาโค้ด) อาการคือกดปุ่มแล้วหน้าไม่ตอบสนอง ตรงกับการกดก่อนหน้าโหลด JavaScript เสร็จ (hydration) · GitHub Actions CI run #107 บน commit 24a0107 เดียวกันผ่าน · ต้องรันซ้ำด้วย npm run test:e2e ตามปกติก่อนสรุปว่าเป็นบัค | K3: tests/e2e/full-billing-lifecycle.spec.ts | L3: evidence-ui/TC_UI_BILL_001.png | M3: 46324.801 | N3: รอยืนยัน — ยังไม่ออก Defect ID
B4: TC_UI_KEY_005 | C4: เมนูและ modal ฝั่งผู้เช่าใช้คีย์บอร์ดได้ | F4: 1. ใช้ Tab ไปตามเมนูผู้เช่า 2. เปิด modal ด้วย Enter แล้วปิดด้วย Escape | G4: เปิดทุกเมนูได้ · modal กัก focus และคืน focus หลังปิด | H4: ไม่ผ่าน: Error: expect(locator).toBeVisible() failed Locator: getByLabel('รายละเอียดบิล E2E-202607-E101', { exact: true }) Expected: visible Timeout: 5000ms Error: element(s) not found Call log: - Expect "toBeVisible" with timeout 5000ms - waiting for getByLabel('รายละเอียดบิล E2E-202607-E101', { exact: true }) | ^ at D:\ปี4_1\it-project\.claude\e2e-run\tests\e2e\keyboard-f | I4: ข้อสังเกต: ไม่ผ่านซ้ำในสภาพแวดล้อมรอบนี้ (next dev --webpack จากสำเนาโค้ด) อาการคือกดปุ่มแล้วหน้าไม่ตอบสนอง ตรงกับการกดก่อนหน้าโหลด JavaScript เสร็จ (hydration) · GitHub Actions CI run #107 บน commit 24a0107 เดียวกันผ่าน · ต้องรันซ้ำด้วย npm run test:e2e ตามปกติก่อนสรุปว่าเป็นบัค | K4: tests/e2e/keyboard-flows.spec.ts | L4: evidence-ui/TC_UI_KEY_005.png | M4: 46324.804 | N4: รอยืนยัน — ยังไม่ออก Defect ID
B5: TC_UI_TENANT_002 | C5: ผู้เช่าแจ้งซ่อมและส่งข้อความแชทถึงหอพัก | F5: 1. เมนูแจ้งเรื่อง → กดแจ้งเรื่อง 2. กรอกหัวข้อ รายละเอียด เลือกความเร่งด่วน "ด่วน" → ส่งเรื่อง 3. กดเปิดแชทกับหอพัก → พิมพ์ข้อความ → ส่งข้อความ | G5: เรื่อง "ก๊อกน้ำ E2E รั่ว" ปรากฏพร้อมป้าย "ด่วน" · ข้อความแชทแสดงในหน้าต่างแชท | H5: ไม่ผ่าน: Error: expect(locator).toBeVisible() failed Locator: getByRole('dialog', { name: 'แชทกับหอพัก' }).getByText('ข้อความ E2E 1793276140216', { exact: true }) Expected: visible Timeout: 5000ms Error: element(s) not found Call log: - Expect "toBeVisible" with timeout 5000ms - waiting for getByRole('dialog', { name: 'แชทกับหอพัก' }).getByText('ข้อความ E2E 1793276140216', { exact: true }) | | I5: ข้อสังเกต: ไม่ผ่านซ้ำในสภาพแวดล้อมรอบนี้ (next dev --webpack จากสำเนาโค้ด) อาการคือกดปุ่มแล้วหน้าไม่ตอบสนอง ตรงกับการกดก่อนหน้าโหลด JavaScript เสร็จ (hydration) · GitHub Actions CI run #107 บน commit 24a0107 เดียวกันผ่าน · ต้องรันซ้ำด้วย npm run test:e2e ตามปกติก่อนสรุปว่าเป็นบัค | K5: tests/e2e/tenant-owner-journeys.spec.ts | L5: evidence-ui/TC_UI_TENANT_002.png | M5: 46324.803 | N5: รอยืนยัน — ยังไม่ออก Defect ID
