Workbook

Sheet สรุปผล
B2: รายงานผลการทดสอบระบบ Nestly (Unit + Integration / API)
B3: ตรรกะธุรกิจ การตรวจข้อมูล สิทธิ์ และ route handler ของ API ทดสอบกับ PostgreSQL จริง
B5: รอบการทดสอบ | C5: Unit 2026-10-29 18:46:18 (2 วินาที) · Integration 2026-10-29 18:46:47 (26 วินาที)
B6: เครื่องมือ | C6: Vitest 4.1.11 · Prisma 7.9.1 · PostgreSQL 17.10 (Docker) · Node.js 22.19
B7: สภาพแวดล้อม | C7: Unit: Node.js 22.19 · Vitest 4.1.11 · Windows 11 (ไม่ใช้ฐานข้อมูล) Integration: DEV (localhost) · PostgreSQL 17.10 ใน Docker (ฐาน nestly_test) · Node.js 22.19 · Windows 11
B8: ผู้รับผิดชอบการทดสอบ
B9: รายงานละเอียด / หลักฐาน | C9: ผล JSON ของ Vitest อยู่ในโฟลเดอร์ evidence-api/ (unit.json, integration.json)
B10: ช่องสีเหลือง = ให้กรอกเอง · ตัวเลขด้านล่างเป็นสูตรที่นับจากชีต Test Cases (แก้คอลัมน์ Status แล้วตัวเลขเปลี่ยนตาม)
B12: ภาพรวม
B13: ตัวชี้วัด | C13: ทั้งหมด | D13: Pass | E13: Fail | F13: Block | G13: Untested | H13: อัตราผ่าน
B14: จำนวนเคส | C14: =COUNTA('Test Cases'!$A$3:$A$300) | D14: =COUNTIF('Test Cases'!$I$3:$I$300,"Pass") | E14: =COUNTIF('Test Cases'!$I$3:$I$300,"Fail") | F14: =COUNTIF('Test Cases'!$I$3:$I$300,"Block") | G14: =COUNTIF('Test Cases'!$I$3:$I$300,"Untested") | H14: =IF(C14-G14=0,0,D14/(C14-G14))
B15: อัตราผ่าน = Pass ÷ (ทั้งหมด − Untested)
B17: ประวัติการรัน
B18: รอบ | C18: วันเวลา | D18: ทั้งหมด | E18: Pass | F18: Fail | G18: Block | H18: อัตราผ่าน
B19: รอบที่ 1 — รันเพื่อจัดทำรายงาน | C19: 2026-10-29 18:46 | D19: =C14 | E19: =D14 | F19: =E14 | G19: =F14 | H19: =IF(D19=0,0,E19/D19)
B21: แยกตามระดับการทดสอบ
B22: ระดับ | C22: ทั้งหมด | D22: Pass | E22: Fail | F22: Block | G22: Untested | H22: อัตราผ่าน
B23: Unit test (Vitest) | C23: =COUNTIF('Test Cases'!$A$3:$A$300,"TC_UNIT_*") | D23: =COUNTIFS('Test Cases'!$A$3:$A$300,"TC_UNIT_*",'Test Cases'!$I$3:$I$300,"Pass") | E23: =COUNTIFS('Test Cases'!$A$3:$A$300,"TC_UNIT_*",'Test Cases'!$I$3:$I$300,"Fail") | F23: =COUNTIFS('Test Cases'!$A$3:$A$300,"TC_UNIT_*",'Test Cases'!$I$3:$I$300,"Block") | G23: =COUNTIFS('Test Cases'!$A$3:$A$300,"TC_UNIT_*",'Test Cases'!$I$3:$I$300,"Untested") | H23: =IF(C23-G23=0,0,D23/(C23-G23))
B24: Integration test (Vitest + PostgreSQL) | C24: =COUNTIF('Test Cases'!$A$3:$A$300,"TC_INT_*") | D24: =COUNTIFS('Test Cases'!$A$3:$A$300,"TC_INT_*",'Test Cases'!$I$3:$I$300,"Pass") | E24: =COUNTIFS('Test Cases'!$A$3:$A$300,"TC_INT_*",'Test Cases'!$I$3:$I$300,"Fail") | F24: =COUNTIFS('Test Cases'!$A$3:$A$300,"TC_INT_*",'Test Cases'!$I$3:$I$300,"Block") | G24: =COUNTIFS('Test Cases'!$A$3:$A$300,"TC_INT_*",'Test Cases'!$I$3:$I$300,"Untested") | H24: =IF(C24-G24=0,0,D24/(C24-G24))
B26: แยกตามส่วนของระบบ / โมดูล
B27: Module / Feature | C27: ทั้งหมด | D27: Pass | E27: Fail | F27: Block | G27: Untested | H27: อัตราผ่าน
B28: Client Error Handling | C28: =COUNTIF('Test Cases'!$B$3:$B$300,$B28) | D28: =COUNTIFS('Test Cases'!$B$3:$B$300,$B28,'Test Cases'!$I$3:$I$300,"Pass") | E28: =COUNTIFS('Test Cases'!$B$3:$B$300,$B28,'Test Cases'!$I$3:$I$300,"Fail") | F28: =COUNTIFS('Test Cases'!$B$3:$B$300,$B28,'Test Cases'!$I$3:$I$300,"Block") | G28: =COUNTIFS('Test Cases'!$B$3:$B$300,$B28,'Test Cases'!$I$3:$I$300,"Untested") | H28: =IF(C28-G28=0,0,D28/(C28-G28))
B29: Subscription UI State | C29: =COUNTIF('Test Cases'!$B$3:$B$300,$B29) | D29: =COUNTIFS('Test Cases'!$B$3:$B$300,$B29,'Test Cases'!$I$3:$I$300,"Pass") | E29: =COUNTIFS('Test Cases'!$B$3:$B$300,$B29,'Test Cases'!$I$3:$I$300,"Fail") | F29: =COUNTIFS('Test Cases'!$B$3:$B$300,$B29,'Test Cases'!$I$3:$I$300,"Block") | G29: =COUNTIFS('Test Cases'!$B$3:$B$300,$B29,'Test Cases'!$I$3:$I$300,"Untested") | H29: =IF(C29-G29=0,0,D29/(C29-G29))
B30: CSV Export | C30: =COUNTIF('Test Cases'!$B$3:$B$300,$B30) | D30: =COUNTIFS('Test Cases'!$B$3:$B$300,$B30,'Test Cases'!$I$3:$I$300,"Pass") | E30: =COUNTIFS('Test Cases'!$B$3:$B$300,$B30,'Test Cases'!$I$3:$I$300,"Fail") | F30: =COUNTIFS('Test Cases'!$B$3:$B$300,$B30,'Test Cases'!$I$3:$I$300,"Block") | G30: =COUNTIFS('Test Cases'!$B$3:$B$300,$B30,'Test Cases'!$I$3:$I$300,"Untested") | H30: =IF(C30-G30=0,0,D30/(C30-G30))
B31: PDF Generation | C31: =COUNTIF('Test Cases'!$B$3:$B$300,$B31) | D31: =COUNTIFS('Test Cases'!$B$3:$B$300,$B31,'Test Cases'!$I$3:$I$300,"Pass") | E31: =COUNTIFS('Test Cases'!$B$3:$B$300,$B31,'Test Cases'!$I$3:$I$300,"Fail") | F31: =COUNTIFS('Test Cases'!$B$3:$B$300,$B31,'Test Cases'!$I$3:$I$300,"Block") | G31: =COUNTIFS('Test Cases'!$B$3:$B$300,$B31,'Test Cases'!$I$3:$I$300,"Untested") | H31: =IF(C31-G31=0,0,D31/(C31-G31))
B32: File Storage (S3) | C32: =COUNTIF('Test Cases'!$B$3:$B$300,$B32) | D32: =COUNTIFS('Test Cases'!$B$3:$B$300,$B32,'Test Cases'!$I$3:$I$300,"Pass") | E32: =COUNTIFS('Test Cases'!$B$3:$B$300,$B32,'Test Cases'!$I$3:$I$300,"Fail") | F32: =COUNTIFS('Test Cases'!$B$3:$B$300,$B32,'Test Cases'!$I$3:$I$300,"Block") | G32: =COUNTIFS('Test Cases'!$B$3:$B$300,$B32,'Test Cases'!$I$3:$I$300,"Untested") | H32: =IF(C32-G32=0,0,D32/(C32-G32))
B33: Document Templates | C33: =COUNTIF('Test Cases'!$B$3:$B$300,$B33) | D33: =COUNTIFS('Test Cases'!$B$3:$B$300,$B33,'Test Cases'!$I$3:$I$300,"Pass") | E33: =COUNTIFS('Test Cases'!$B$3:$B$300,$B33,'Test Cases'!$I$3:$I$300,"Fail") | F33: =COUNTIFS('Test Cases'!$B$3:$B$300,$B33,'Test Cases'!$I$3:$I$300,"Block") | G33: =COUNTIFS('Test Cases'!$B$3:$B$300,$B33,'Test Cases'!$I$3:$I$300,"Untested") | H33: =IF(C33-G33=0,0,D33/(C33-G33))
B34: Account Approval | C34: =COUNTIF('Test Cases'!$B$3:$B$300,$B34) | D34: =COUNTIFS('Test Cases'!$B$3:$B$300,$B34,'Test Cases'!$I$3:$I$300,"Pass") | E34: =COUNTIFS('Test Cases'!$B$3:$B$300,$B34,'Test Cases'!$I$3:$I$300,"Fail") | F34: =COUNTIFS('Test Cases'!$B$3:$B$300,$B34,'Test Cases'!$I$3:$I$300,"Block") | G34: =COUNTIFS('Test Cases'!$B$3:$B$300,$B34,'Test Cases'!$I$3:$I$300,"Untested") | H34: =IF(C34-G34=0,0,D34/(C34-G34))
B35: Billing | C35: =COUNTIF('Test Cases'!$B$3:$B$300,$B35) | D35: =COUNTIFS('Test Cases'!$B$3:$B$300,$B35,'Test Cases'!$I$3:$I$300,"Pass") | E35: =COUNTIFS('Test Cases'!$B$3:$B$300,$B35,'Test Cases'!$I$3:$I$300,"Fail") | F35: =COUNTIFS('Test Cases'!$B$3:$B$300,$B35,'Test Cases'!$I$3:$I$300,"Block") | G35: =COUNTIFS('Test Cases'!$B$3:$B$300,$B35,'Test Cases'!$I$3:$I$300,"Untested") | H35: =IF(C35-G35=0,0,D35/(C35-G35))
B36: Chat | C36: =COUNTIF('Test Cases'!$B$3:$B$300,$B36) | D36: =COUNTIFS('Test Cases'!$B$3:$B$300,$B36,'Test Cases'!$I$3:$I$300,"Pass") | E36: =COUNTIFS('Test Cases'!$B$3:$B$300,$B36,'Test Cases'!$I$3:$I$300,"Fail") | F36: =COUNTIFS('Test Cases'!$B$3:$B$300,$B36,'Test Cases'!$I$3:$I$300,"Block") | G36: =COUNTIFS('Test Cases'!$B$3:$B$300,$B36,'Test Cases'!$I$3:$I$300,"Untested") | H36: =IF(C36-G36=0,0,D36/(C36-G36))
B37: Domain Rules | C37: =COUNTIF('Test Cases'!$B$3:$B$300,$B37) | D37: =COUNTIFS('Test Cases'!$B$3:$B$300,$B37,'Test Cases'!$I$3:$I$300,"Pass") | E37: =COUNTIFS('Test Cases'!$B$3:$B$300,$B37,'Test Cases'!$I$3:$I$300,"Fail") | F37: =COUNTIFS('Test Cases'!$B$3:$B$300,$B37,'Test Cases'!$I$3:$I$300,"Block") | G37: =COUNTIFS('Test Cases'!$B$3:$B$300,$B37,'Test Cases'!$I$3:$I$300,"Untested") | H37: =IF(C37-G37=0,0,D37/(C37-G37))
B38: Lease | C38: =COUNTIF('Test Cases'!$B$3:$B$300,$B38) | D38: =COUNTIFS('Test Cases'!$B$3:$B$300,$B38,'Test Cases'!$I$3:$I$300,"Pass") | E38: =COUNTIFS('Test Cases'!$B$3:$B$300,$B38,'Test Cases'!$I$3:$I$300,"Fail") | F38: =COUNTIFS('Test Cases'!$B$3:$B$300,$B38,'Test Cases'!$I$3:$I$300,"Block") | G38: =COUNTIFS('Test Cases'!$B$3:$B$300,$B38,'Test Cases'!$I$3:$I$300,"Untested") | H38: =IF(C38-G38=0,0,D38/(C38-G38))
B39: Occupancy | C39: =COUNTIF('Test Cases'!$B$3:$B$300,$B39) | D39: =COUNTIFS('Test Cases'!$B$3:$B$300,$B39,'Test Cases'!$I$3:$I$300,"Pass") | E39: =COUNTIFS('Test Cases'!$B$3:$B$300,$B39,'Test Cases'!$I$3:$I$300,"Fail") | F39: =COUNTIFS('Test Cases'!$B$3:$B$300,$B39,'Test Cases'!$I$3:$I$300,"Block") | G39: =COUNTIFS('Test Cases'!$B$3:$B$300,$B39,'Test Cases'!$I$3:$I$300,"Untested") | H39: =IF(C39-G39=0,0,D39/(C39-G39))
... B82: Tenant Portal | C82: =COUNTIF('Test Cases'!$B$3:$B$300,$B82) | D82: =COUNTIFS('Test Cases'!$B$3:$B$300,$B82,'Test Cases'!$I$3:$I$300,"Pass") | E82: =COUNTIFS('Test Cases'!$B$3:$B$300,$B82,'Test Cases'!$I$3:$I$300,"Fail") | F82: =COUNTIFS('Test Cases'!$B$3:$B$300,$B82,'Test Cases'!$I$3:$I$300,"Block") | G82: =COUNTIFS('Test Cases'!$B$3:$B$300,$B82,'Test Cases'!$I$3:$I$300,"Untested") | H82: =IF(C82-G82=0,0,D82/(C82-G82))

Sheet แผนการทดสอบ
B2: แผนการทดสอบ (Test Plan)
B3: Nestly — การทดสอบระดับโค้ดและ API (Unit + Integration)
B5: 1. วัตถุประสงค์
B6: • ยืนยันว่าตรรกะธุรกิจ (คิดค่าเช่า ค่าน้ำไฟ ค่าปรับ มัดจำ แพ็กเกจ) คำนวณถูกต้อง
B7: • ยืนยันว่าการตรวจข้อมูลด้วย Zod ปฏิเสธข้อมูลผิด ฟิลด์แปลกปลอม และค่าขอบ
B8: • ยืนยันการยืนยันตัวตน session สิทธิ์ตามบทบาท ความเป็นเจ้าของข้อมูล CSRF และการอัปโหลดไฟล์ กับฐานข้อมูลจริง
B10: 2. ขอบเขตการทดสอบ
B11: อยู่ในขอบเขต (รอบนี้) | C11: Unit 123 เคส (lib/**/*.test.ts) · Integration 94 เคส (tests/integration/*.test.ts)
B12: นอกขอบเขต | C12: การตรวจสิทธิ์แบบไล่ทุก endpoint (ดูชีต ช่องว่างการทดสอบ) · การทดสอบโหลด · ผู้ให้บริการภายนอกจริง (S3 จริง)
B13: ทดสอบในระดับอื่นแล้ว | C13: หน้าจอและเส้นทางผู้ใช้ครอบด้วย Playwright (ดูไฟล์ Nestly-UI-Test-Report.xlsx)
B15: 3. รายการที่ทดสอบ (Test Items)
B16: ส่วนของระบบ | C16: ตำแหน่งโค้ด | D16: เทคโนโลยี | E16: ข้อมูลทดสอบ
B17: ตรรกะธุรกิจและ validation | C17: lib/domain, lib/server, lib/documents | D17: TypeScript + Zod 4 | E17: ค่าคงที่ในไฟล์เทสต์
B18: Route handler ของ API | C18: app/api/**/route.ts | D18: Next.js 16 Route Handlers | E18: fixture สร้างใหม่ทุกไฟล์ (tests/integration/helpers.ts)
B19: ฐานข้อมูล | C19: prisma/schema.prisma + migrations | D19: PostgreSQL 17 + Prisma 7.9 | E19: ฐาน nestly_test แยกจากฐาน dev
B21: 4. สภาพแวดล้อมการทดสอบ
B22: Unit | C22: Node.js 22.19 · ไม่ใช้ฐานข้อมูล · S3 จำลองด้วย vi.mock
B23: Integration | C23: PostgreSQL 17.10 ใน Docker (docker-compose.e2e.yml, timezone UTC, tmpfs) · migrate deploy ก่อนรัน · รันทีละไฟล์ timeout 30 วินาที
B24: ไฟล์อัปโหลด | C24: STORAGE_TYPE=local · LOCAL_STORAGE_PATH=./storage/test-documents
B26: 5. เกณฑ์เริ่มและเกณฑ์จบ
B27: เกณฑ์เริ่ม (Entry) | C27: npm ci สำเร็จ · prisma generate · ฐานทดสอบ migrate ครบ (สำหรับ integration)
B28: เกณฑ์จบ (Exit) | C28: ทุกเคสผ่าน 100% · CI job quality และ integration เป็นสีเขียว
B29: การรันซ้ำ | C29: npm test · npm run test:integration · npm run test:coverage (รายงาน coverage ส่ง SonarQube)

Sheet กลยุทธ์การทดสอบ
B2: กลยุทธ์การทดสอบ (Test Strategy)
B3: ทดสอบอะไร ด้วยวิธีไหน ระดับไหน และจัดการผลอย่างไร
B5: 1. ระดับการทดสอบ (Test Levels)
B6: ระดับ | C6: เครื่องมือ | D6: ทดสอบอะไร | E6: รันเมื่อไร
B7: Unit | C7: Vitest | D7: ฟังก์ชันคำนวณ schema ของ Zod นโยบายสิทธิ์ ตัวช่วย UI | E7: ทุก push / pull request (CI job quality)
B8: Integration | C8: Vitest + PostgreSQL | D8: route handler จริง service และ transaction กับฐานข้อมูลจริง | E8: ทุก push / pull request (CI job integration)
B9: Static / Security | C9: TypeScript strict · ESLint · npm audit · SonarQube | D9: ชนิดข้อมูล กลิ่นโค้ด dependency ที่มีช่องโหว่ | E9: ทุก push / pull request และทุกวันจันทร์
B11: 2. ประเภทและเทคนิคการทดสอบ
B12: เทคนิค | C12: ตัวอย่างในรายงานนี้
B13: Positive | C13: TC_UNIT_BILL_002, TC_INT_AUTH_002, TC_INT_FLOW_001
B14: Negative | C14: TC_UNIT_BILL_004, TC_UNIT_CHAT_001, TC_UNIT_LEASE_004
B15: Boundary Value | C15: TC_UNIT_BILL_003, TC_UNIT_CHAT_002, TC_UNIT_LEASE_002, TC_UNIT_TICKET_002, TC_UNIT_PAGE_003
B16: Equivalence Partitioning | C16: TC_UNIT_PAY_001, TC_UNIT_TAUTH_001
B17: Security (Auth / Session) | C17: TC_INT_AUTH_002, TC_INT_SESSION_001, TC_INT_SESSION_002, TC_INT_BRUTE_001, TC_INT_DOC_005
B18: Security (IDOR / RBAC) | C18: TC_UNIT_NAV_003, TC_UNIT_RBAC_002, TC_INT_OWN_002, TC_INT_CHAT_004, TC_INT_CONFLICT_008
B19: Security (CSRF / XSS / Upload) | C19: TC_UNIT_STORE_005, TC_UNIT_TPL_001, TC_UNIT_SIG_001, TC_UNIT_TAUTH_002, TC_INT_DOC_001
B20: State Transition | C20: TC_UNIT_ENUM_002, TC_INT_CONFLICT_004
B21: Concurrency / Transaction | C21: TC_UNIT_LEASE_005, TC_INT_CONFLICT_001, TC_INT_JOB_001, TC_INT_TX_001
B23: 3. การจัดการข้อมูลทดสอบ
B24: Integration fixture | C24: createIntegrationFixture() สร้างเจ้าของหอ 2 คน (คนละหอ) Super Admin อาคาร ชั้น ห้อง ชื่อลงท้ายด้วยตัวสุ่ม แล้วลบทิ้งใน afterAll
B25: ด่านกันพลาด | C25: assertTestDatabase() ปฏิเสธฐานที่ชื่อไม่มีคำว่า test ก่อนลบหรือเขียนข้อมูล
B26: ค่าคงที่ของ Unit | C26: ข้อมูลอยู่ในไฟล์เทสต์ เวลาอ้างอิงตั้งตายตัว (เช่น 2026-07-29) ผลจึงไม่ขึ้นกับวันที่รัน
B28: 4. การจัดการผลและข้อบกพร่อง
B29: • Status ใช้ 4 ค่า: Pass / Fail / Block / Untested · เคส Fail ต้องวิเคราะห์ก่อนออก Defect ID
B30: • CI ล้มเมื่อมีเคสไม่ผ่าน ทำให้ merge ไม่ได้จนกว่าจะแก้

Sheet Test Cases
A1: 1. ข้อมูลระดับโครงสร้างและเคสทดสอบ (Test Setup) | H1: 2. ผลการทดสอบและการแจ้งบัค (Execution & Bug Tracking) | L1: 3. การบันทึกและจัดการ (Metadata & Evidence)
A2: Test Case ID | B2: Module / Feature | C2: Test Scenario / Title | D2: Pre-conditions | E2: Test Steps | F2: Test Data | G2: Expected Result | H2: Actual Result | I2: Status | J2: Defect ID / Bug Link | K2: Severity / Priority | L2: Environment | M2: Tester Name | N2: Execution Date | O2: Screenshot / Evidence Link | P2: Remarks / Note
A3: TC_UNIT_ERR_C_001 | B3: Client Error Handling | C3: แสดงรหัสอ้างอิง (request ID) ต่อท้ายข้อความ error ที่ผู้ใช้เห็น | D3: ไม่ต้องใช้ฐานข้อมูล · เรียกฟังก์ชันโดยตรงใน Vitest | E3: 1. สร้าง error จาก API ที่มี requestId 2. เรียก formatClientError() | F3: error = "บันทึกไม่สำเร็จ" requestId = "req-123" | G3: ได้ข้อความ "บันทึกไม่สำเร็จ (รหัสอ้างอิง: req-123)" | H3: ผลตรงตามที่คาดหวัง — assertion ผ่านครบ (0.00 วินาที) | I3: Pass | L3: Node.js 22.19 · Vitest 4.1.11 · Windows 11 (ไม่ใช้ฐานข้อมูล) | M3: Vitest 4.1.11 (อัตโนมัติ) | N3: 46324.782 | O3: ผลรายเคสอยู่ในไฟล์ JSON ของ Vitest (evidence-api/) | P3: สคริปต์: lib/client/api-error.test.ts ชื่อเทสต์: client API errors includes the request ID in the user-facing error
A4: TC_UNIT_ERR_C_002 | B4: Client Error Handling | C4: error ที่ไม่รู้จักต้องแสดงข้อความกลางที่ปลอดภัย | D4: ไม่ต้องใช้ฐานข้อมูล · เรียกฟังก์ชันโดยตรงใน Vitest | E4: 1. เรียก formatClientError(null, ข้อความสำรอง) | F4: error = null fallback = "ไม่สามารถดำเนินการได้" | G4: ได้ข้อความสำรอง "ไม่สามารถดำเนินการได้" ไม่เผยรายละเอียดภายใน | H4: ผลตรงตามที่คาดหวัง — assertion ผ่านครบ (0.00 วินาที) | I4: Pass | L4: Node.js 22.19 · Vitest 4.1.11 · Windows 11 (ไม่ใช้ฐานข้อมูล) | M4: Vitest 4.1.11 (อัตโนมัติ) | N4: 46324.782 | O4: ผลรายเคสอยู่ในไฟล์ JSON ของ Vitest (evidence-api/) | P4: สคริปต์: lib/client/api-error.test.ts ชื่อเทสต์: client API errors uses a safe fallback for unknown errors
A5: TC_UNIT_ERR_C_003 | B5: Client Error Handling | C5: อ่าน requestId จาก body ของ API ที่ตอบ error | D5: ไม่ต้องใช้ฐานข้อมูล · เรียกฟังก์ชันโดยตรงใน Vitest | E5: 1. สร้าง Response สถานะ 409 ที่มี error + requestId 2. เรียก readApiPayload() | F5: HTTP 409 body = {"error":"บันทึกไม่สำเร็จ","requestId":"req-body"} | G5: ได้ error ที่มี message "บันทึกไม่สำเร็จ" และ requestId "req-body" | H5: ผลตรงตามที่คาดหวัง — assertion ผ่านครบ (0.04 วินาที) | I5: Pass | L5: Node.js 22.19 · Vitest 4.1.11 · Windows 11 (ไม่ใช้ฐานข้อมูล) | M5: Vitest 4.1.11 (อัตโนมัติ) | N5: 46324.782 | O5: ผลรายเคสอยู่ในไฟล์ JSON ของ Vitest (evidence-api/) | P5: สคริปต์: lib/client/api-error.test.ts ชื่อเทสต์: client API errors preserves a request ID from an API error envelope
A6: TC_UNIT_ERR_C_004 | B6: Client Error Handling | C6: body ไม่ใช่ JSON ต้องใช้ requestId จาก header แทน | D6: ไม่ต้องใช้ฐานข้อมูล · เรียกฟังก์ชันโดยตรงใน Vitest | E6: 1. สร้าง Response 502 ที่ body เป็นข้อความธรรมดา 2. เรียก readApiPayload() | F6: HTTP 502 body = "not-json" x-request-id = req-header | G6: ได้ error ข้อความสำรอง "ระบบไม่พร้อม" และ requestId "req-header" | H6: ผลตรงตามที่คาดหวัง — assertion ผ่านครบ (0.00 วินาที) | I6: Pass | L6: Node.js 22.19 · Vitest 4.1.11 · Windows 11 (ไม่ใช้ฐานข้อมูล) | M6: Vitest 4.1.11 (อัตโนมัติ) | N6: 46324.782 | O6: ผลรายเคสอยู่ในไฟล์ JSON ของ Vitest (evidence-api/) | P6: สคริปต์: lib/client/api-error.test.ts ชื่อเทสต์: client API errors uses the response header request ID when the body is invalid
A7: TC_UNIT_ERR_C_005 | B7: Client Error Handling | C7: อ่านข้อมูลจากรูปแบบคำตอบสำเร็จมาตรฐาน { data, requestId } | D7: ไม่ต้องใช้ฐานข้อมูล · เรียกฟังก์ชันโดยตรงใน Vitest | E7: 1. สร้าง Response 200 แบบมาตรฐาน 2. เรียก readApiData() | F7: body = {"data":{"id":"1"},"requestId":"req-ok"} | G7: ได้ข้อมูล {"id":"1"} | H7: ผลตรงตามที่คาดหวัง — assertion ผ่านครบ (0.00 วินาที) | I7: Pass | L7: Node.js 22.19 · Vitest 4.1.11 · Windows 11 (ไม่ใช้ฐานข้อมูล) | M7: Vitest 4.1.11 (อัตโนมัติ) | N7: 46324.782 | O7: ผลรายเคสอยู่ในไฟล์ JSON ของ Vitest (evidence-api/) | P7: สคริปต์: lib/client/api-error.test.ts ชื่อเทสต์: client API errors returns data from the standard success envelope
A8: TC_UNIT_SUB_UI_001 | B8: Subscription UI State | C8: แปลงสถานะแพ็กเกจจาก API (maps FULL API access to full) เป็นสถานะหน้าจอ | D8: ไม่ต้องใช้ฐานข้อมูล · เรียกฟังก์ชันโดยตรงใน Vitest | E8: 1. เรียก resolveSubscriptionUiAccessState({ accessMode }) หรือ blocksSubscriptionMutations(state) | F8: maps FULL API access to full | G8: ได้ค่าตามตาราง: FULL→full, GRACE→grace, READ_ONLY→read-only · loading/error/read-only ห้ามแก้ไขข้อมูล ส่วน full/grace แก้ไขได้ | H8: ผลตรงตามที่คาดหวัง — assertion ผ่านครบ (0.00 วินาที) | I8: Pass | L8: Node.js 22.19 · Vitest 4.1.11 · Windows 11 (ไม่ใช้ฐานข้อมูล) | M8: Vitest 4.1.11 (อัตโนมัติ) | N8: 46324.782 | O8: ผลรายเคสอยู่ในไฟล์ JSON ของ Vitest (evidence-api/) | P8: สคริปต์: lib/client/subscription-access-state.test.ts ชื่อเทสต์: subscription UI access state maps FULL API access to full
A9: TC_UNIT_SUB_UI_002 | B9: Subscription UI State | C9: แปลงสถานะแพ็กเกจจาก API (maps GRACE API access to grace) เป็นสถานะหน้าจอ | D9: ไม่ต้องใช้ฐานข้อมูล · เรียกฟังก์ชันโดยตรงใน Vitest | E9: 1. เรียก resolveSubscriptionUiAccessState({ accessMode }) หรือ blocksSubscriptionMutations(state) | F9: maps GRACE API access to grace | G9: ได้ค่าตามตาราง: FULL→full, GRACE→grace, READ_ONLY→read-only · loading/error/read-only ห้ามแก้ไขข้อมูล ส่วน full/grace แก้ไขได้ | H9: ผลตรงตามที่คาดหวัง — assertion ผ่านครบ (0.00 วินาที) | I9: Pass | L9: Node.js 22.19 · Vitest 4.1.11 · Windows 11 (ไม่ใช้ฐานข้อมูล) | M9: Vitest 4.1.11 (อัตโนมัติ) | N9: 46324.782 | O9: ผลรายเคสอยู่ในไฟล์ JSON ของ Vitest (evidence-api/) | P9: สคริปต์: lib/client/subscription-access-state.test.ts ชื่อเทสต์: subscription UI access state maps GRACE API access to grace
A10: TC_UNIT_SUB_UI_003 | B10: Subscription UI State | C10: แปลงสถานะแพ็กเกจจาก API (maps READ_ONLY API access to read-only) เป็นสถานะหน้าจอ | D10: ไม่ต้องใช้ฐานข้อมูล · เรียกฟังก์ชันโดยตรงใน Vitest | E10: 1. เรียก resolveSubscriptionUiAccessState({ accessMode }) หรือ blocksSubscriptionMutations(state) | F10: maps READ_ONLY API access to read-only | G10: ได้ค่าตามตาราง: FULL→full, GRACE→grace, READ_ONLY→read-only · loading/error/read-only ห้ามแก้ไขข้อมูล ส่วน full/grace แก้ไขได้ | H10: ผลตรงตามที่คาดหวัง — assertion ผ่านครบ (0.00 วินาที) | I10: Pass | L10: Node.js 22.19 · Vitest 4.1.11 · Windows 11 (ไม่ใช้ฐานข้อมูล) | M10: Vitest 4.1.11 (อัตโนมัติ) | N10: 46324.782 | O10: ผลรายเคสอยู่ในไฟล์ JSON ของ Vitest (evidence-api/) | P10: สคริปต์: lib/client/subscription-access-state.test.ts ชื่อเทสต์: subscription UI access state maps READ_ONLY API access to read-only
A11: TC_UNIT_SUB_UI_004 | B11: Subscription UI State | C11: แยกสถานะกำลังโหลด / โหลดผิดพลาด ออกจากสถานะอ่านอย่างเดียวจริง | D11: ไม่ต้องใช้ฐานข้อมูล · เรียกฟังก์ชันโดยตรงใน Vitest | E11: 1. เรียกด้วย isLoading=true 2. เรียกด้วย error 3. เรียกด้วยค่าว่าง | F11: isLoading=true · error="network error" · {} | G11: ได้ "loading", "error", "error" ตามลำดับ (ไม่สรุปว่าแพ็กเกจหมดอายุ) | H11: ผลตรงตามที่คาดหวัง — assertion ผ่านครบ (0.00 วินาที) | I11: Pass | L11: Node.js 22.19 · Vitest 4.1.11 · Windows 11 (ไม่ใช้ฐานข้อมูล) | M11: Vitest 4.1.11 (อัตโนมัติ) | N11: 46324.782 | O11: ผลรายเคสอยู่ในไฟล์ JSON ของ Vitest (evidence-api/) | P11: สคริปต์: lib/client/subscription-access-state.test.ts ชื่อเทสต์: subscription UI access state distinguishes loading and errors from confirmed read-only access
A12: TC_UNIT_SUB_UI_005 | B12: Subscription UI State | C12: ระหว่างรีเฟรชเบื้องหลังต้องคงสิทธิ์ที่ยืนยันแล้วไว้ | D12: ไม่ต้องใช้ฐานข้อมูล · เรียกฟังก์ชันโดยตรงใน Vitest | E12: 1. accessMode=FULL พร้อม isLoading 2. accessMode=GRACE พร้อม error | F12: FULL + isLoading · GRACE + error | G12: ได้ "full" และ "grace" ตามเดิม | H12: ผลตรงตามที่คาดหวัง — assertion ผ่านครบ (0.00 วินาที) | I12: Pass | L12: Node.js 22.19 · Vitest 4.1.11 · Windows 11 (ไม่ใช้ฐานข้อมูล) | M12: Vitest 4.1.11 (อัตโนมัติ) | N12: 46324.782 | O12: ผลรายเคสอยู่ในไฟล์ JSON ของ Vitest (evidence-api/) | P12: สคริปต์: lib/client/subscription-access-state.test.ts ชื่อเทสต์: subscription UI access state keeps confirmed access during a background refresh or refresh error
A13: TC_UNIT_SUB_UI_006 | B13: Subscription UI State | C13: หน้าที่ไม่ได้อยู่ในบริบทหอพัก ไม่ถูกจำกัดสิทธิ์ | D13: ไม่ต้องใช้ฐานข้อมูล · เรียกฟังก์ชันโดยตรงใน Vitest | E13: 1. เรียกด้วย enabled=false, isLoading=true | F13: enabled=false | G13: ได้ "full" | H13: ผลตรงตามที่คาดหวัง — assertion ผ่านครบ (0.00 วินาที) | I13: Pass | L13: Node.js 22.19 · Vitest 4.1.11 · Windows 11 (ไม่ใช้ฐานข้อมูล) | M13: Vitest 4.1.11 (อัตโนมัติ) | N13: 46324.782 | O13: ผลรายเคสอยู่ในไฟล์ JSON ของ Vitest (evidence-api/) | P13: สคริปต์: lib/client/subscription-access-state.test.ts ชื่อเทสต์: subscription UI access state does not restrict screens without an active property context
A14: TC_UNIT_SUB_UI_007 | B14: Subscription UI State | C14: แปลงสถานะแพ็กเกจจาก API (maps loading to mutation blocked=true) เป็นสถานะหน้าจอ | D14: ไม่ต้องใช้ฐานข้อมูล · เรียกฟังก์ชันโดยตรงใน Vitest | E14: 1. เรียก resolveSubscriptionUiAccessState({ accessMode }) หรือ blocksSubscriptionMutations(state) | F14: maps loading to mutation blocked=true | G14: ได้ค่าตามตาราง: FULL→full, GRACE→grace, READ_ONLY→read-only · loading/error/read-only ห้ามแก้ไขข้อมูล ส่วน full/grace แก้ไขได้ | H14: ผลตรงตามที่คาดหวัง — assertion ผ่านครบ (0.00 วินาที) | I14: Pass | L14: Node.js 22.19 · Vitest 4.1.11 · Windows 11 (ไม่ใช้ฐานข้อมูล) | M14: Vitest 4.1.11 (อัตโนมัติ) | N14: 46324.782 | O14: ผลรายเคสอยู่ในไฟล์ JSON ของ Vitest (evidence-api/) | P14: สคริปต์: lib/client/subscription-access-state.test.ts ชื่อเทสต์: subscription UI access state maps loading to mutation blocked=true
... A219: TC_INT_TENANT_010 | B219: Tenant Portal | C219: ผู้พักร่วมดูรายการบิลไม่ได้ | D219: ฐานข้อมูลทดสอบ nestly_test (migrate ครบ) · fixture: เจ้าของหอ A, เจ้าของหอ B (คนละหอ), Super Admin, ห้องทดสอบ · ผู้เช่าหลักและผู้พักร่วมของห้องทดสอบ | E219: 1. listTenantInvoices() ผู้พักร่วม | F219: role = CO_OCCUPANT | G219: HTTP 403 | H219: ผลตรงตามที่คาดหวัง — assertion ผ่านครบ (0.00 วินาที) | I219: Pass | L219: DEV (localhost) · PostgreSQL 17.10 ใน Docker (ฐาน nestly_test) · Node.js 22.19 · Windows 11 | M219: Vitest 4.1.11 (อัตโนมัติ) | N219: 46324.783 | O219: ผลรายเคสอยู่ในไฟล์ JSON ของ Vitest (evidence-api/) | P219: สคริปต์: tests/integration/tenant-portal.test.ts ชื่อเทสต์: tenant portal read model refuses to list invoices for a co-occupant

Sheet Defects
A1: รายการข้อบกพร่อง (Defect Log) — ออก Defect ID เฉพาะเคสที่วิเคราะห์แล้วว่าเป็นบัคของระบบ
A2: Defect ID | B2: Test Case ID | C2: Title | D2: Severity | E2: Priority | F2: Steps to Reproduce | G2: Expected Result | H2: Actual Result | I2: ผลกระทบต่อผู้ใช้ | J2: แนวทางแก้ (Suggested Fix) | K2: ไฟล์ที่เกี่ยวข้อง | L2: Evidence (ตอนพบบัค) | M2: Found Date | N2: Defect Status | O2: การแก้ไขที่ทำ | P2: ผลทดสอบซ้ำ (Retest) | Q2: หลักฐานหลังแก้
A3: รอบนี้ไม่พบข้อบกพร่อง — ทุกเคสผ่าน (ถ้ารันรอบใหม่แล้วมีเคส Fail ให้วิเคราะห์ก่อนออก Defect ID)

Sheet ช่องว่างการทดสอบ
A1: ช่องว่างของชุดทดสอบ — สิ่งที่ยังไม่ได้ทดสอบหรือทดสอบได้ไม่เต็มที่ และคำแนะนำ
A2: ID | B2: หมวด | C2: สิ่งที่ยังขาด | D2: ผลกระทบถ้าเกิดปัญหา | E2: ระดับ | F2: คำแนะนำ
A3: GAP-01 | B3: Security | C3: ยังไม่มีเทสต์ที่ไล่ตรวจสิทธิ์ทุก endpoint (ทุก method × ทุกบทบาท) แบบอัตโนมัติ ตอนนี้ตรวจเป็นจุด ๆ | D3: endpoint ใหม่ที่ลืมใส่การตรวจสิทธิ์จะไม่มีเทสต์จับได้ | E3: High | F3: สร้างเทสต์ที่อ่านรายการ route จาก app/api แล้วยิงด้วยทุกบทบาท เทียบกับตารางสิทธิ์ที่คาดหวัง
A4: GAP-02 | B4: Cross-browser | C4: E2E รันเฉพาะ Chromium | D4: ผู้ใช้ Safari บน iPhone อาจเจอปัญหาที่ไม่ถูกตรวจ | E4: Medium | F4: เพิ่ม project webkit และ firefox ใน playwright.config.ts อย่างน้อยสำหรับเส้นทางหลัก
A5: GAP-03 | B5: Performance | C5: ไม่มีการทดสอบโหลดหรือเวลาตอบของ API | D5: ไม่รู้ขีดจำกัดเมื่อมีผู้ใช้พร้อมกันจำนวนมาก | E5: Medium | F5: ใช้ k6 หรือ autocannon ยิง endpoint หลักบนเครื่อง staging
A6: GAP-04 | B6: Mobile | C6: ทดสอบมือถือด้วยการจำลองขนาดจอ ไม่ใช่อุปกรณ์จริง | D6: ปัญหาเฉพาะอุปกรณ์ (คีย์บอร์ดเสมือน, safe area) ไม่ถูกตรวจ | E6: Low | F6: ทดสอบด้วยมือบนมือถือจริงก่อนส่งงาน หรือใช้บริการอุปกรณ์จริงบนคลาวด์
A7: GAP-05 | B7: Coverage | C7: รายงานนี้ไม่ได้วัด code coverage | D7: ไม่รู้ว่าโค้ดส่วนไหนไม่มีเทสต์ครอบ | E7: Low | F7: รัน npm run test:coverage และ test:coverage:integration แล้วดูผลใน SonarQube
A8: GAP-06 | B8: Storage | C8: S3 ทดสอบด้วยการจำลอง ไม่ได้ต่อบริการจริง | D8: ค่าตั้ง bucket หรือสิทธิ์ผิดบนระบบจริงจะไม่ถูกตรวจ | E8: Low | F8: เพิ่ม smoke test หลัง deploy ที่อัปโหลดและลบไฟล์ทดสอบหนึ่งไฟล์
